opengater_globalauth_client/__init__.py
opengater_globalauth_client/client.py
opengater_globalauth_client/exceptions.py
opengater_globalauth_client/models.py
opengater_globalauth_client/broker/__init__.py
opengater_globalauth_client/broker/consumer.py
opengater_globalauth_client/broker/events.py
opengater_globalauth_client/broker/publisher.py
opengater_globalauth_client/fastapi/__init__.py
opengater_globalauth_client/fastapi/dependencies.py
opengater_globalauth_client/fastapi/middleware.py
opengater_globalauth_client-0.1.6.dist-info/METADATA
opengater_globalauth_client-0.1.6.dist-info/WHEEL
opengater_globalauth_client-0.1.6.dist-info/RECORD
