Metadata-Version: 2.4
Name: opengater-globalauth-client
Version: 0.1.6
Summary: Client library for GlobalAuth authentication service
Project-URL: Homepage, https://github.com/opengater/globalauth-client
Project-URL: Documentation, https://github.com/opengater/globalauth-client#readme
Author: Opengater
License: MIT
Keywords: auth,authentication,fastapi,rabbitmq
Classifier: Development Status :: 4 - Beta
Classifier: Framework :: FastAPI
Classifier: Intended Audience :: Developers
Classifier: License :: OSI Approved :: MIT License
Classifier: Programming Language :: Python :: 3
Classifier: Programming Language :: Python :: 3.11
Classifier: Programming Language :: Python :: 3.12
Classifier: Programming Language :: Python :: 3.13
Classifier: Topic :: Security
Requires-Python: >=3.11
Requires-Dist: fastapi>=0.100.0
Requires-Dist: faststream[rabbit]>=0.5.0
Requires-Dist: httpx>=0.27.0
Requires-Dist: pydantic>=2.0.0
